scTenifold/__init__.py
scTenifold/__main__.py
scTenifold/cell_cycle/UCell.py
scTenifold/cell_cycle/__init__.py
scTenifold/cell_cycle/scoring.py
scTenifold/core/_QC.py
scTenifold/core/__init__.py
scTenifold/core/_base.py
scTenifold/core/_decomposition.py
scTenifold/core/_ko.py
scTenifold/core/_networks.py
scTenifold/core/_norm.py
scTenifold/core/_utils.py
scTenifold/data/__init__.py
scTenifold/data/_get.py
scTenifold/data/_io.py
scTenifold/data/_sim.py
scTenifold/plotting/__init__.py
scTenifold/plotting/_dim_reduction.py
scTenifold/plotting/_plotting.py
scTenifoldpy-0.1.3.dist-info/LICENSE
scTenifoldpy-0.1.3.dist-info/METADATA
scTenifoldpy-0.1.3.dist-info/WHEEL
scTenifoldpy-0.1.3.dist-info/entry_points.txt
scTenifoldpy-0.1.3.dist-info/top_level.txt
scTenifoldpy-0.1.3.dist-info/RECORD
