Metadata-Version: 2.1
Name: scTenifoldpy
Version: 0.1.3
Summary: scTenifoldpy
Home-page: https://github.com/qwerty239qwe/scTenifoldpy
Author: Yu-Te Lin
Author-email: qwerty239qwe@gmail.com
License: MIT
Classifier: License :: OSI Approved :: MIT License
Classifier: Programming Language :: Python :: 3
Classifier: Programming Language :: Python :: 3.7
License-File: LICENSE
Requires-Dist: pandas (~=1.2.5)
Requires-Dist: numpy (~=1.20.3)
Requires-Dist: scipy (~=1.6.3)
Requires-Dist: setuptools (~=56.2.0)
Requires-Dist: typer (~=0.4.0)
Requires-Dist: PyYAML (~=5.4.1)
Requires-Dist: ray (~=1.8.0)
Requires-Dist: scikit-learn (~=0.24.2)
Requires-Dist: tensorly (~=0.6.0)
Requires-Dist: requests (~=2.26.0)
Requires-Dist: seaborn (~=0.11.1)
Requires-Dist: matplotlib (~=3.4.3)
Requires-Dist: networkx (~=2.6.3)
Requires-Dist: scanpy (~=1.7.2)
Requires-Dist: protobuf (==3.20.*)
